Metadata-Version: 1.0
Name: Metaphone
Version: 0.4
Summary: A Python implementation of the metaphone algorithms.
Home-page: https://github.com/oubiwann/metaphone
Author: Andrew Collins
Author-email: AtomBoy@SWCP.com
License: BSD
Platform: UNKNOWN
